MooQuant-0.3.8.dist-info/METADATA
MooQuant-0.3.8.dist-info/RECORD
MooQuant-0.3.8.dist-info/WHEEL
MooQuant-0.3.8.dist-info/top_level.txt
mooquant/__init__.py
mooquant/bar.py
mooquant/dispatcher.py
mooquant/dispatchprio.py
mooquant/eventprofiler.py
mooquant/logger.py
mooquant/marketsession.py
mooquant/observer.py
mooquant/plotter.py
mooquant/resamplebase.py
mooquant/warninghelpers.py
mooquant/analyzer/__init__.py
mooquant/analyzer/drawdown.py
mooquant/analyzer/returns.py
mooquant/analyzer/sharpe.py
mooquant/analyzer/trades.py
mooquant/barfeed/__init__.py
mooquant/barfeed/common.py
mooquant/barfeed/csvfeed.py
mooquant/barfeed/dbfeed.py
mooquant/barfeed/membf.py
mooquant/barfeed/mootdxfeed.py
mooquant/barfeed/ninjatraderfeed.py
mooquant/barfeed/quandlfeed.py
mooquant/barfeed/resampled.py
mooquant/barfeed/sqlitefeed.py
mooquant/barfeed/tusharefeed.py
mooquant/broker/__init__.py
mooquant/broker/backtesting.py
mooquant/broker/fillstrategy.py
mooquant/broker/slippage.py
mooquant/dataseries/__init__.py
mooquant/dataseries/aligned.py
mooquant/dataseries/bards.py
mooquant/dataseries/resampled.py
mooquant/feed/__init__.py
mooquant/feed/csvfeed.py
mooquant/feed/memfeed.py
mooquant/optimizer/__init__.py
mooquant/optimizer/base.py
mooquant/optimizer/local.py
mooquant/optimizer/server.py
mooquant/optimizer/worker.py
mooquant/optimizer/xmlrpcserver.py
mooquant/optimizer/zmqrpcserver.py
mooquant/provider/__init__.py
mooquant/provider/bar.py
mooquant/provider/csvfeed.py
mooquant/provider/bitcoincharts/__init__.py
mooquant/provider/bitcoincharts/barfeed.py
mooquant/provider/bitstamp/__init__.py
mooquant/provider/bitstamp/barfeed.py
mooquant/provider/bitstamp/broker.py
mooquant/provider/bitstamp/common.py
mooquant/provider/bitstamp/httpclient.py
mooquant/provider/bitstamp/livebroker.py
mooquant/provider/bitstamp/livefeed.py
mooquant/provider/bitstamp/wsclient.py
mooquant/provider/xignite/__init__.py
mooquant/provider/xignite/api.py
mooquant/provider/xignite/barfeed.py
mooquant/strategy/__init__.py
mooquant/strategy/position.py
mooquant/talibext/__init__.py
