Metadata-Version: 2.1
Name: MooQuant
Version: 0.3.8
Summary: MooQuant
Home-page: http://www.mooquant.com/
Author: bopowang
Author-email: ibopo@126.com
License: MIT license
Download-URL: https://github.com/bopo/mooquant/archive/master.zip
Keywords: mooquant
Platform: UNKNOWN
Classifier: Development Status :: 2 - Pre-Alpha
Classifier: Intended Audience :: Developers
Classifier: License :: OSI Approved :: MIT License
Classifier: Natural Language :: English
Classifier: Programming Language :: Python :: 3
Classifier: Programming Language :: Python :: 3.3
Classifier: Programming Language :: Python :: 3.4
Classifier: Programming Language :: Python :: 3.5
Classifier: Programming Language :: Python :: 3.6
Classifier: Programming Language :: Python :: 3.7
Provides-Extra: Bitstamp
Provides-Extra: Scipy
Provides-Extra: TALib
Provides-Extra: Plotting
Requires-Dist: click (>=6.0)
Requires-Dist: python-dateutil
Requires-Dist: requests
Requires-Dist: numpy
Requires-Dist: pytz
Provides-Extra: Bitstamp
Requires-Dist: ws4py (>=0.3.4); extra == 'Bitstamp'
Requires-Dist: tornado (==4.5.3); extra == 'Bitstamp'
Provides-Extra: Plotting
Requires-Dist: matplotlib; extra == 'Plotting'
Provides-Extra: Scipy
Requires-Dist: scipy; extra == 'Scipy'
Provides-Extra: TALib
Requires-Dist: Cython; extra == 'TALib'
Requires-Dist: TA-Lib; extra == 'TALib'
